{
    "Office Phone": "250.861.8315",
    "Fax": "250.861.8325",
    "E-Mail": "cpears@wecarecanada.com",
    "Website": "www.cbi.ca\/web\/we-care-home-health-services",
    "Additional Info": "www.cbi.ca\/web\/home-health-kelowna-spall-we-care",
    "Primary Contact": "Charlene Pears, RN, Branch Director",
    "Social Media": "Facebook: www.facebook.com\/cbihealthgroupLinkedIn: www.linkedin.com\/company\/857948\/Twitter: twitter.com\/CBIHealthGroup",
    "Service Details": "- Provides in-home companion care, homemaking, personal support, and family support in home and in institutions- Also supports the community with flu and wellness clinics as well as foot care",
    "Cost": "Please call for additional information on services and our fee structure",
    "Address & Map": "2000 Spall Rd, #270Kelowna, BC     V1Y 9P6View MapQuest Map",
    "Located In Community": "Kelowna",
    "Major Intersection": "Dickson Ave and Kirschner Ave",
    "Coordinates": [
        "49.8774480",
        "-119.4546670"
    ]
}