{
    "Office Phone": "250.862.9088",
    "Fax": "250.862.9097",
    "Website": "www.siennaliving.ca\/retirement\/locations\/okanagan-chateau-retirement-residence.aspx",
    "Social Media": "Facebook: www.facebook.com\/siennaliving\/Google+: plus.google.com\/+SiennaSeniorLivingMarkhamLinkedIn: www.linkedin.com\/company\/333290YouTube: www.youtube.com\/channel\/UCvxoh3wc8hmfG8gwCYyCh-g",
    "Service Details": "- Provides independent, supportive housing- Also offers short-term stays",
    "Cost": "Fee for service",
    "Address & Map": "2100 Benvoulin CrtKelowna, BC     V1W 3A4View MapQuest Map",
    "Located In Community": "Kelowna",
    "Major Intersection": "Benvoulin Crt and Springfield Rd",
    "Languages": "English",
    "Coordinates": [
        "49.8761800",
        "-119.4423640"
    ]
}