{
    "Office Phone": "Rutland: 250.980.4825Kelowna: 250.469.7070Westbank: 250.980.5150",
    "Fax": "250.868.7809",
    "Website": "www.interiorhealth.ca",
    "Additional Info": "www.interiorhealth.ca\/FindUs\/_layouts\/FindUs\/info.aspx?type=Service&loc=&svc=Baby%20Talk&ploc=",
    "Social Media": "Facebook: www.facebook.com\/InteriorHealthLinkedIn: www.linkedin.com\/company\/interior-health-authorityTwitter: twitter.com\/Interior_HealthYouTube: www.youtube.com\/user\/InteriorHealthAuth",
    "Service Details": "Offers an informal, 1-hour, weekly drop-in support group for families with babies that discusses various health related topics ranging from nutritional requirements to infant massage to safety and childhood illness.Locations:- Kelowna: Community Health & Services Centre (505 Doyle Avenue, Kelowna)- Rutland: Rutland Health Centre (155 Gray Road, Kelowna)- West Kelowna: West Kelowna Health Centre (106-2300 Carrington Road, West Kelowna)",
    "Dates": "1:30pm - 2:30pm: Rutland, Mon; West Kelowna, Tue; Kelowna, Wed",
    "Eligibility": "Ages: 6 year(s) and under",
    "Cost": "None",
    "Located In Community": "Kelowna"
}