{
    "Office Phone": "778.797.0791",
    "Website": "www.newmoonartgallerykelowna.com",
    "Primary Contact": "Linda Lovisa, Art Class Instructor",
    "Social Media": "Facebook: www.facebook.com\/NewMoonGalleryTwitter: twitter.com\/NewMoonGallery",
    "Service Details": "- Offers art classes for children, acrylic and watercolour classes, drawing classes, plein air painting, pastel classes, basket weaving workshops, and self-exploration creative workshops- Offers works of art for sale- Hosts art shows and events with refreshment and music",
    "Hours": "Mon-Fri: 10:00am - 5:00pmSat: 10:00am - 4:00pm",
    "Eligibility": "Ages: 7 year(s) and up",
    "Cost": "Service ; Please visit the website for details on fees",
    "Address & Map": "1726 Byland Rd, #3West Kelowna, BC     V1Z 1A9",
    "Located In Community": "West Kelowna",
    "Major Intersection": "Dobbin Rd and Elliott Rd",
    "Languages": "English",
    "Coordinates": [
        "49.8615630",
        "-119.5890650"
    ]
}