{
    "Office Phone": "250.870.8991",
    "Toll Free Phone": "1.888.495.4440 (Foster Parent Support Line)",
    "E-Mail": "coksupport@okfosterparents.ca",
    "Website": "www.okfosterparents.ca",
    "Primary Contact": "Nicole McFadyen, Foster Parent Coordinator; Email: coksupport@okfosterparents.ca",
    "Social Media": "Facebook: www.facebook.com\/okfosterparents",
    "Service Details": "Strengthens foster care by providing education, training and support services for foster parents of children placed by the Ministry of Children and Family Development",
    "Address & Map": "1503 MacLeay CrtKelowna, BC     V1Y 9L6View MapQuest Map",
    "Located In Community": "Kelowna",
    "Major Intersection": "MacLeay Ct and Clifton Rd",
    "Coordinates": [
        "49.8989690",
        "-119.4653200"
    ]
}