{
    "Office Phone": "250.862.8866",
    "E-Mail": "csc@centralkelowna.com",
    "Website": "www.centralsportsclub.net",
    "Social Media": "Facebook: www.facebook.com\/CSCkelownaTwitter: twitter.com\/CSCkelowna",
    "Service Details": "- Offers an indoor sports arena with ball hockey, volleyball, basketball, and futsal leagues- Provides an event venue, for birthdays, staff parties, sports events, etc.- Visit Facebook page or website for drop-in info",
    "Address & Map": "1155 Ellis StKelowna, BC     V1Y 1Z4",
    "Located In Community": "Kelowna",
    "Major Intersection": "Ellis St and Cannery Lane",
    "Languages": "English",
    "Former Name": "Sunplex Sports Arena",
    "Coordinates": [
        "49.8944730",
        "-119.4930680"
    ]
}