{
    "Mailing Address": "c\/o Central Okanagan Heritage Society1060 Cameron AveKelowna, BC     V1Y 8V3",
    "Office Phone": "250.861.7188",
    "E-Mail": "cohs@telus.net",
    "Website": "www.okheritagesociety.com",
    "CanadaHelps Donation Page": "www.canadahelps.org\/en\/charities\/central-okanagan-heritage-society\/",
    "Primary Contact": "Lorri Dauncey, Heritage Planning and Projects Director & City of Kelowna Heritage Grants Manager; Phone: 250.861.7188; Email: ldauncey.cohs@telus.net",
    "Alternate Contact": "Shannon Jorgenson, Managing Director; Phone: 250.861.7188; Email: sjorgenson.cohs@telus.net",
    "Primary Executive": "Don Knox, President; Email: cdknox@shaw.ca",
    "Social Media": "Facebook: www.facebook.com\/OkHeritageSociety",
    "Service Details": "- Preserves and restores heritage buildings and heritage conservation- Manages Guisachan Heritage Park and owns Benvoulin Heritage Church, Reid Hall, McIver House, and McDougall House- Manages the City of Kelowna Heritage Grants Program (CoKHGP)- Offers facilities and halls for rent",
    "Hours": "Office Hours: Mon,Wed,Thu: 10:00am - 3:00pm",
    "Meetings": "Annual public AGM each March",
    "Address & Map": "537 Bernard Ave, #3Kelowna, BC     V1Y 6N9View MapQuest Map",
    "Located In Community": "Kelowna",
    "Accessibility": "Wheelchair accessible at Benvoulin Heritage Church and Reid Hall",
    "Languages": "English",
    "Established": "1982",
    "Print Material": "Newsletter published two times a year",
    "Coordinates": [
        "49.8863040",
        "-119.4922980"
    ]
}