{
    "Mailing Address": "731 Trench StKelowna, BC     V1Y 7M9",
    "Office Phone": "250.868.2704",
    "Fax": "250.868.0463",
    "E-Mail": "order@urbanharvest.ca",
    "Website": "www.urbanharvest.ca",
    "Primary Contact": "Lisa McIntosh, Owner",
    "Service Details": "- Provides convenient and affordable organic foods to the Central Okanagan area- Contributes to a local food culture that celebrates healthy, joyful eating- Committed to being part of a sustainable food system- Reduces distance from field to table by working closely with Okanagan farmers and offering as much locally grown produce as possible (annual average approximately 50%)- Donates leftover produce to the Kelowna Community Food Bank each week - Culled or spoiled produce is used by a local farm for animal feed and compost- Offers reduced prices on organic produce at Warehouse Sales each Saturday",
    "Hours": "Warehouse Sales: Sat: 9:00am - 1:00pm",
    "Address & Map": "806A Crowley AveKelowna, BC     V1Y 7G7View MapQuest Map",
    "Located In Community": "Kelowna",
    "Major Intersection": "Crowley Ave and Richter St",
    "Coordinates": [
        "49.8983370",
        "-119.4855290"
    ]
}