{
    "Office Phone": "250.762.3112",
    "Fax": "250.762.0486",
    "E-Mail": "info@kelownacurling.com",
    "Website": "www.kelownacurling.com",
    "Primary Contact": "Brendan Willis, President; Email: brendan.Willis@raymondjames.ca",
    "Service Details": "Provides competitive and non-competitive curling for all ages",
    "Cost": "Please visit our website for details on fees",
    "Address & Map": "551 Recreation AveKelowna, BC     V1Y 7V5",
    "Located In Community": "Kelowna",
    "Major Intersection": "Recreation Ave and Ellis St",
    "Languages": "English",
    "Coordinates": [
        "49.8971950",
        "-119.4920490"
    ]
}