{
    "Mailing Address": "c\/o LarryShipowick793 West Point DrKelowna, BC     V1W 2Z4",
    "Office Phone": "250.764.8638",
    "Website": "www.chiphealth.com",
    "Primary Contact": "Dr Larry Shipowick, DDS MPH; Phone: 250.864.4047; Email: larryshipowick@yahoo.ca",
    "Social Media": "Facebook: www.facebook.com\/Kelowna-CHIP-524854211035331\/",
    "Service Details": "Offers a 4-week lifestyle education program that provides educational support for those concerned about Western lifestyle diseases such as diabetes, heart attack, stroke, osteoporosis, hypertension, and cancer that includes a complete risk assessment, matching blood work taken prior to the course with that taken 30 days after",
    "Cost": "Program - nominal",
    "Meetings": "Please call for info on the Free Info Sessions, Lifestyle Education Program, and Monthly CHIP Club meetings",
    "Address & Map": "Kelowna Life Style Center1130 Springfield RdKelowna, BC     V1Y 5T5View MapQuest Map",
    "Located In Community": "Kelowna",
    "Major Intersection": "Springfield Rd and Gordon Dr",
    "Languages": "English"
}