{
    "Office Phone": "236.420.2581",
    "Toll Free Phone": "1.844.874.2848",
    "Fax": "236.420.2583",
    "E-Mail": "admin@kelownadentureclinic.com",
    "Website": "www.kelownadenture.com\/",
    "Alternate Contact": "Stacey MacAulay, Denturist",
    "Primary Executive": "Tyler Perrault, Owner and Denturist",
    "Social Media": "Facebook: www.facebook.com\/kelownadentureclinicInstagram: www.instagram.com\/kelownadentureclinicTwitter: twitter.com\/kelownadentures",
    "Service Details": "- Offers denture care that includes implant-supported dentures, precision dentures, cast partial dentures, immediate dentures, relines, rebases, soft liners, and repairs- Offers free consultation, coordinated treatment planning, photo documentation, one year of complementary adjustments post-insertion, and an annual recare program for five years post-insertion- Also provides nursing home calls and after hours availability upon request",
    "Hours": "Mon: 9:00am - 5:00pmTue: 8:00am - 5:00pmWed: 8:00am - 5:00pmThu: 9:00am - 5:00pm",
    "Cost": "Service",
    "Address & Map": "1824 Gordon Dr, Unit 102Kelowna, BC     V1Y 0E2",
    "Located In Community": "Kelowna",
    "Major Intersection": "Gordon Dr and Bordon Ave",
    "Accessibility": "Partially Accessible - parking and clinic are accessible; entrance is manually operated (front door is heavy)",
    "Languages": "English",
    "Coordinates": [
        "49.8813610",
        "-119.4773760"
    ]
}