{
    "Office Phone": "1.800.268.3062",
    "E-Mail": "info@walksokidscantalk.ca",
    "Website": "walksokidscantalk.ca\/",
    "Social Media": "Facebook: www.facebook.com\/KidsHelpPhoneTwitter: twitter.com\/kidshelpphoneYouTube: www.youtube.com\/user\/KidsHelpPhone",
    "Service Details": "Raises funds for KidsHelpPhone to keep services available to kids across Canada 24\/7 and help support their emotional health",
    "How to Apply": "To create a volunteer account for 2017 volunteer positions, please visit our website and select the Kelowna location",
    "Located In Community": "Canada",
    "Languages": "English"
}