{
    "Office Phone": "250.765.5125 ext.231",
    "Fax": "250.765.0213",
    "E-Mail": "ylwairportwatch@kelowna.ca",
    "Website": "ylw.kelowna.ca\/about-ylw\/volunteer-ylw",
    "Social Media": "Facebook: www.facebook.com\/ylw.kelownaairportInstagram: www.instagram.com\/ylwkelowna\/Twitter: twitter.com\/ylwkelowna",
    "Service Details": "- Provides volunteer-driven program that increases safety and security at Kelowna International Airport- Airport Watch volunteers provide the same sort of security as the Neighbourhood Watch Program- Members monitor general aviation procedures, the condition of fencing, wildlife activity, parking lots, suspicious behaviours and flying debris- Members task is to \"Observe, Record and Report\"",
    "Address & Map": "5533 Airport Way, Ste 1Kelowna, BC     V1V 1S1",
    "Located In Community": "Kelowna",
    "Accessibility": "Not Accessible",
    "Languages": "English",
    "Coordinates": [
        "49.9510560",
        "-119.3810800"
    ]
}