{
    "Mailing Address": "2600 Hebert RdWest Kelowna, BC     V4T 2J6",
    "Office Phone": "250.769.1174",
    "E-Mail": "contact@schoolsbeyondborders.com",
    "Service Details": "- Assists local students to expand their understanding of other cultures and encourages them to take an active role in global relationships- Provides funding, supplies and tools to needy schools in third world and developing countries- Establishes and provides scholarships and\/or bursaries for needy students in third world or developing countries to attain a higher level of education",
    "Located In Community": "International",
    "Accessibility": "Not Accessible",
    "Languages": "English"
}