{
    "Mailing Address": "c\/o Myrna Thompson, Okanagan Region Ride Manager and Director, BC Competitive Trail Riders Association4497 Shanks RdLake Country, BC     V4V 1M3",
    "Office Phone": "250.317.8347",
    "After Hours Phone": "250.317.8347",
    "E-Mail": "Equiessence@hotmail.com",
    "Website": "www.bcctra.ca",
    "Primary Contact": "Myrna Thompson, Okanagan Region Ride Manager and Director; Phone: 250.317.8347; Email: Equiessence@hotmail.com",
    "Primary Executive": "Nancy Gourlay, President; Phone: 250.954.3941; Email: nancy@cheeseworks.ca",
    "Alternate Executive": "Joanne Macaluso, Caribou Director and Ride Manager; Phone: 250.706.9964 * 250.456.7320; Email: Joanne_macaluso@bcit.ca",
    "Social Media": "Facebook: www.facebook.com\/groups\/244460928976065\/",
    "Service Details": "- Promotes and improves the rapidly growing sport of competitive trail riding in BC - Hosts event patterned after the North American Trail Riding Conference - Volunteer opportunities available",
    "Dates": "Click here for to see the schedule",
    "Located In Community": "Central Okanagan",
    "Languages": "English"
}