{
    "items": [
        {
            "name": "QMUNITY, BC's Queer Resource Centre",
            "address": "1170 Bute StVancouver, BC     V6E 1Z6&nbsp;View MapQuest Map",
            "phone": "1.604.684.5307 ext.100",
            "link": "https:\/\/kelowna.cioc.ca\/record\/KNA0094?Number=0"
        },
        {
            "name": "Quest Martial Arts",
            "address": "1634 Harvey Ave, #108Kelowna, BC     V1Y 6G2",
            "phone": "250.869.0111",
            "link": "https:\/\/kelowna.cioc.ca\/record\/KNA0418?Number=1"
        },
        {
            "name": "Quit Now, BC Lung Association",
            "address": "2675 Oak StVancouver, BC     V6H 2K2&nbsp;View MapQuest Map",
            "phone": "811 (ask to be connected to the QuitNow Program)",
            "link": "https:\/\/kelowna.cioc.ca\/record\/KNA1056?Number=2"
        },
        {
            "name": "Quota International of Penticton",
            "address": "250.488.2398",
            "phone": "",
            "link": "https:\/\/kelowna.cioc.ca\/record\/KNA2067?Number=3"
        }
    ],
    "url": "https:\/\/kelowna.cioc.ca\/browsebyorg.asp?Let=Q"
}